{
  "follows": [
    {
      "user_id": "1115180309748654080",
      "username": "otasou_toyoR18",
      "date": "2026-03-04",
      "timestamp": "2026-03-04T01:56:25.384652"
    },
    {
      "user_id": "1807744892883681280",
      "username": "zucca0702",
      "date": "2026-03-04",
      "timestamp": "2026-03-04T01:56:40.499850"
    },
    {
      "user_id": "1166401767581446144",
      "username": "Darkness_Fairy_",
      "date": "2026-03-04",
      "timestamp": "2026-03-04T01:56:55.616354"
    },
    {
      "user_id": "1921441211568840705",
      "username": "gajetblog",
      "date": "2026-03-04",
      "timestamp": "2026-03-04T01:57:10.750293"
    },
    {
      "user_id": "88604205",
      "username": "luckeater",
      "date": "2026-03-04",
      "timestamp": "2026-03-04T01:57:25.876848"
    },
    {
      "user_id": "268118087",
      "username": "miyuki_ayashi",
      "date": "2026-03-04",
      "timestamp": "2026-03-04T01:57:40.997433"
    },
    {
      "user_id": "143757914",
      "username": "smileybottsu",
      "date": "2026-03-04",
      "timestamp": "2026-03-04T01:57:56.310949"
    },
    {
      "user_id": "162635173",
      "username": "ZOA_numahon",
      "date": "2026-03-04",
      "timestamp": "2026-03-04T01:58:11.442059"
    },
    {
      "user_id": "1840888671853043712",
      "username": "BambieRags93625",
      "date": "2026-03-04",
      "timestamp": "2026-03-04T01:58:26.553600"
    },
    {
      "user_id": "1758407897430818816",
      "username": "AI_Bridge_Japan",
      "date": "2026-03-04",
      "timestamp": "2026-03-04T01:58:41.676103"
    },
    {
      "user_id": "12100092",
      "username": "miyakawa2449",
      "date": "2026-03-04",
      "timestamp": "2026-03-04T01:58:56.787250"
    },
    {
      "user_id": "1113029784496332801",
      "username": "rakkomacom",
      "date": "2026-03-04",
      "timestamp": "2026-03-04T01:59:11.903077"
    },
    {
      "user_id": "114189264",
      "username": "3pasopia",
      "date": "2026-03-04",
      "timestamp": "2026-03-04T01:59:27.025846"
    },
    {
      "user_id": "1542051945137184768",
      "username": "PK_chiba",
      "date": "2026-03-04",
      "timestamp": "2026-03-04T01:59:42.179419"
    },
    {
      "user_id": "1923496049035051008",
      "username": "w041017",
      "date": "2026-03-04",
      "timestamp": "2026-03-04T01:59:57.290952"
    }
  ],
  "last_run": "2026-03-04T02:00:12.291078"
}